caas/__init__.py
caas/cli.py
caas/conversation.py
caas/decay.py
caas/enrichment.py
caas/hf_utils.py
caas/models.py
caas/pragmatic_truth.py
caas/triad.py
caas/api/__init__.py
caas/api/server.py
caas/detection/__init__.py
caas/detection/detector.py
caas/gateway/__init__.py
caas/gateway/trust_gateway.py
caas/ingestion/__init__.py
caas/ingestion/processors.py
caas/ingestion/structure_parser.py
caas/routing/__init__.py
caas/routing/heuristic_router.py
caas/storage/__init__.py
caas/storage/store.py
caas/tuning/__init__.py
caas/tuning/tuner.py
caas/vfs/__init__.py
caas/vfs/filesystem.py
caas_core-0.3.0.dist-info/licenses/LICENSE
caas_core-0.3.0.dist-info/METADATA
caas_core-0.3.0.dist-info/WHEEL
caas_core-0.3.0.dist-info/entry_points.txt
caas_core-0.3.0.dist-info/top_level.txt
caas_core-0.3.0.dist-info/RECORD
