Metadata-Version: 2.4
Name: caas-core
Version: 0.3.0
Summary: A pure, logic-only library for routing context, handling RAG fallacies, and managing context windows. Layer 1 Primitive - no agent dependencies.
Author: Imran Siddique
License-Expression: MIT
Project-URL: Homepage, https://github.com/imran-siddique/context-as-a-service
Project-URL: Repository, https://github.com/imran-siddique/context-as-a-service
Project-URL: Documentation, https://github.com/imran-siddique/context-as-a-service/tree/main/docs
Project-URL: Issues, https://github.com/imran-siddique/context-as-a-service/issues
Keywords: context,rag,document-processing,ai,nlp,context-extraction,context-routing,context-window,rag-fallacies,stateless,primitive
Classifier: Development Status :: 3 - Alpha
Classifier: Intended Audience :: Developers
Classifier: Programming Language :: Python :: 3
Classifier: Programming Language :: Python :: 3.8
Classifier: Programming Language :: Python :: 3.9
Classifier: Programming Language :: Python :: 3.10
Classifier: Programming Language :: Python :: 3.11
Classifier: Programming Language :: Python :: 3.12
Classifier: Topic :: Software Development :: Libraries :: Python Modules
Classifier: Topic :: Scientific/Engineering :: Artificial Intelligence
Requires-Python: >=3.8
License-File: LICENSE
Requires-Dist: fastapi>=0.104.1
Requires-Dist: uvicorn[standard]>=0.24.0
Requires-Dist: pydantic>=2.5.0
Requires-Dist: PyPDF2>=3.0.1
Requires-Dist: beautifulsoup4>=4.12.2
Requires-Dist: lxml>=4.9.3
Requires-Dist: python-multipart>=0.0.6
Requires-Dist: tiktoken>=0.5.1
Requires-Dist: numpy>=1.26.2
Requires-Dist: scikit-learn>=1.3.2
Requires-Dist: aiofiles>=23.2.1
Provides-Extra: dev
Requires-Dist: pytest>=7.4.0; extra == "dev"
Requires-Dist: pytest-cov>=4.1.0; extra == "dev"
Requires-Dist: pytest-asyncio>=0.21.0; extra == "dev"
Requires-Dist: black>=23.0.0; extra == "dev"
Requires-Dist: ruff>=0.1.0; extra == "dev"
Requires-Dist: mypy>=1.5.0; extra == "dev"
Provides-Extra: test
Requires-Dist: pytest>=7.4.0; extra == "test"
Requires-Dist: pytest-cov>=4.1.0; extra == "test"
Requires-Dist: pytest-asyncio>=0.21.0; extra == "test"
Provides-Extra: hf
Requires-Dist: huggingface_hub>=0.20.0; extra == "hf"
Requires-Dist: datasets>=2.16.0; extra == "hf"
Provides-Extra: all
Requires-Dist: caas-core[dev,hf,test]; extra == "all"
Dynamic: license-file
